[{"name":"sql.active_record","payload":{"sql":"SELECT  \"users\".* FROM \"users\"  WHERE \"users\".\"email\" = 'tmerlet@gmail.com' LIMIT 1","name":"User Load","connection_id":70160789453180,"binds":[],"line":9,"filename":"/Users/MB/Documents/IT/Steve/Ramp/app/controllers/sessions_controller.rb","method":"create"},"time":"2014-12-14T19:41:08+00:00","transaction_id":"db6e671a49c4711d00ea","end":"2014-12-14T19:41:08+00:00","duration":0.43600000000000005},{"name":"process_action.action_controller","payload":{"controller":"SessionsController","action":"create","params":{"utf8":"\u2713","authenticity_token":"IcAQnAYeEdMVZ6cCbyg65RJ1rQzWVSMwBohatKlyr1k=","user":{"email":"tmerlet@gmail.com","password":"[FILTERED]","remember_me":"0"},"commit":"Log in","action":"create","controller":"sessions"},"format":"html","method":"POST","path":"/users/sign_in"},"time":"2014-12-14T19:41:08+00:00","transaction_id":"0290c3d188c0c58183b9","end":"2014-12-14T19:41:08+00:00","duration":3.346}]